langchain_decorators/__init__.py
langchain_decorators/chains.py
langchain_decorators/common.py
langchain_decorators/function_decorator.py
langchain_decorators/llm_chat_session.py
langchain_decorators/llm_protocols.py
langchain_decorators/llm_tool_use.py
langchain_decorators/output_parsers.py
langchain_decorators/prompt_decorator.py
langchain_decorators/prompt_decorator.pyi
langchain_decorators/prompt_template.py
langchain_decorators/pydantic_helpers.py
langchain_decorators/schema.py
langchain_decorators/streaming_context.py
langchain_decorators/experimental/__init__.py
langchain_decorators/experimental/prompt_register/base.py
langchain_decorators/experimental/prompt_register/langsmith_register.py
langchain_decorators/langgraph/__init__.py
langchain_decorators/langgraph/graphs.py
langchain_decorators/langgraph/node_decorator.py
langchain_decorators/langgraph/node_tool.py
langchain_decorators/langgraph/nodes_base.py
langchain_decorators/langgraph/transitions.py
langchain_decorators-1.1.0.dist-info/licenses/LICENSE
langchain_decorators-1.1.0.dist-info/METADATA
langchain_decorators-1.1.0.dist-info/WHEEL
langchain_decorators-1.1.0.dist-info/top_level.txt
langchain_decorators-1.1.0.dist-info/RECORD
