Metadata-Version: 2.4
Name: langchain-decorators
Version: 1.1.0
Summary: syntactic sugar for langchain
Author-email: ju-bezdek <juraj.bezdek@gmail.com>
License: MIT
Project-URL: Homepage, https://github.com/ju-bezdek/langchain-decorators
Project-URL: Repository, https://github.com/ju-bezdek/langchain-decorators
Keywords: langchain
Requires-Python: <4.0.0,>=3.11
License-File: LICENSE
Requires-Dist: typing-inspect
Requires-Dist: langchain-core<2.0.0,>=1.0.0
Provides-Extra: langgraph
Requires-Dist: langgraph; extra == "langgraph"
Provides-Extra: dev
Requires-Dist: langgraph; extra == "dev"
Dynamic: license-file
